LICENSE
README.md
setup.py
src/common_structure_microservices/__init__.py
src/common_structure_microservices/authentication.py
src/common_structure_microservices/delete_notification.py
src/common_structure_microservices/entity_url.py
src/common_structure_microservices/exception.py
src/common_structure_microservices/exception_handler.py
src/common_structure_microservices/messages.py
src/common_structure_microservices/models.py
src/common_structure_microservices/notification.py
src/common_structure_microservices/paginator.py
src/common_structure_microservices/permissions.py
src/common_structure_microservices/profiles.py
src/common_structure_microservices/remote.py
src/common_structure_microservices/responses.py
src/common_structure_microservices/send_email.py
src/common_structure_microservices/serializer.py
src/common_structure_microservices/type_notification.py
src/common_structure_microservices/utilities.py
src/common_structure_microservices/view.py
src/common_structure_microservices.egg-info/PKG-INFO
src/common_structure_microservices.egg-info/SOURCES.txt
src/common_structure_microservices.egg-info/dependency_links.txt
src/common_structure_microservices.egg-info/requires.txt
src/common_structure_microservices.egg-info/top_level.txt