Metadata-Version: 1.2
Name: common-structure-microservices
Version: 0.0.51
Summary: Este es un paquete que permite utilizar cosas comunes a los microservicios con solo instalarlo mediante pip
Home-page: https://github.com/fernanxd17, https://github.com/PaolaBird
Author: Paola Pajaro y Fernando Romero
Author-email: juanfernandoro@ufps.edu.co, yindypaolapu@ufps.edu.co
License: UNKNOWN
Download-URL: https://PaolaBird@bitbucket.org/PaolaBird/common_microservices.git
Platform: UNKNOWN
Classifier: Programming Language :: Python :: 3
Classifier: License :: OSI Approved :: MIT License
Classifier: Operating System :: OS Independent
Requires-Python: >=3.6
